continual/__about__.py
continual/__init__.py
continual/closure.py
continual/container.py
continual/conv.py
continual/convert.py
continual/delay.py
continual/linear.py
continual/logging.py
continual/module.py
continual/onnx.py
continual/pooling.py
continual/positional_encoding.py
continual/ptflops.py
continual/rnn.py
continual/shape.py
continual/skip.py
continual/transformer.py
continual/utils.py
continual/multihead_attention/__init__.py
continual/multihead_attention/mha_base.py
continual/multihead_attention/retroactive_mha.py
continual/multihead_attention/single_output_mha.py
continual_inference-1.2.4.dist-info/LICENSE
continual_inference-1.2.4.dist-info/METADATA
continual_inference-1.2.4.dist-info/WHEEL
continual_inference-1.2.4.dist-info/top_level.txt
continual_inference-1.2.4.dist-info/RECORD
